utils_git/__init__.py
utils_git/core/Git.py
utils_git/core/__init__.py
utils_git_nuuuwan-2.0.1.dist-info/LICENSE
utils_git_nuuuwan-2.0.1.dist-info/METADATA
utils_git_nuuuwan-2.0.1.dist-info/WHEEL
utils_git_nuuuwan-2.0.1.dist-info/top_level.txt
utils_git_nuuuwan-2.0.1.dist-info/RECORD
