Metadata-Version: 2.1
Name: utils_git-nuuuwan
Version: 2.0.1
Summary: Basic Git Utilities.
Home-page: https://github.com/nuuuwan/utils_git
Author: Nuwan I. Senaratna
Author-email: nuuuwan@gmail.com
Project-URL: Bug Tracker, https://github.com/nuuuwan/utils_git/issues
Classifier: Programming Language :: Python :: 3
Classifier: License :: OSI Approved :: MIT License
Classifier: Operating System :: OS Independent
Requires-Python: >=3.10
License-File: LICENSE
Requires-Dist: utils-base-nuuuwan
